Q7/Dff.v
module Dff (output q, output  qn, input d, input clk);

	//initial begin
	//	q = 1'b0;
 	//	qn = 1'b1;
	//end

	//assign qn = ~q;
	
	//always @ (posedge clk) begin
		
	//	q <= d;
		 	
	//end
	reg nclk;
	Dl inst1 (qi, qni, d, nclk);
	Dl inst2 (q, qn, qi, clk);
	
	
	always @ (clk) begin
		nclk <= ~clk;
	end
	
	wire qi, qni;
	
	
endmodule


module RSl (output reg q, output reg qn, input r, input s);

	
	always @(q, qn, r, s) begin
		
		q <= ~ (qn | r);
		qn <= ~ (q | s);
		
	end

endmodule

module Dl (output q, output qn, input d, input clk);
	
	reg r, s;
	
	RSl RSlinstDl (q, qn, r, s);
	
	always @ (r, s, d, clk) begin
		r <= (~ d) & clk;
		s <= d & clk;
	end
	

endmodule

Q7/t_Dff.v
/**
*	Test bench for D flip-flop
*	By: Omkar Prabhu 16CO233
*	15th October 2017
*/

`timescale 1ns/100ps

module t_Dff;

	// outputs 
	wire q;
	wire qn;
	// inputs 
	reg d;
	reg clk;
	
	// D flip-flop thread instantiated
	Dff inst (q, qn, d, clk);
	
	// check for various input combinations
	initial begin
	
		$dumpfile("Dff.vcd");
		$dumpvars(0, t_Dff);
		
		d = 1'b0;
		clk = 1'b0;
			
		#6
			d = 1'b1;			
		#6
			d = 1'b0;
		#6
			d = 1'b0;
		#6;
			d = 1'b1;
		#6;
			d = 1'b1;
		#6;
			d = 1'b0;
		#6;
		#6
			d = 1'b1;			
		#6
			d = 1'b0;
		#6
			d = 1'b0;
		#6;
			d = 1'b0;
		#6;
			d = 1'b1;
		#6;
			d = 1'b0;
		#6;
		#6
			d = 1'b1;			
		#6
			d = 1'b1;
		#6
			d = 1'b1;
		#6;
			d = 1'b0;
		#6;
			d = 1'b1;
		#6;
			d = 1'b0;
		#6;
		#6
			d = 1'b1;			
		#6
			d = 1'b0;
		#6
			d = 1'b1;
		#6;
			d = 1'b1;
		#6;
			d = 1'b1;
		#6;
			d = 1'b0;
		#6;
			
	end	
	
	initial begin
		repeat (30) begin
			#5 clk = ~ clk;
		end
	end
	
	// print result
	initial begin
		$monitor("%t: d: %b clk: %b \n\t\t\t q: %b q': %b\n", $time, d, clk, q, qn);	
	end
	
	
endmodule

Q7/Dff.vcd
$date
	Sun Oct 15 23:48:21 2017
$end
$version
	Icarus Verilog
$end
$timescale
	100ps
$end
$scope module t_Dff $end
$var wire 1 ! q $end
$var wire 1 " qn $end
$var reg 1 # clk $end
$var reg 1 $ d $end
$scope module inst $end
$var wire 1 % clk $end
$var wire 1 & d $end
$var wire 1 ! q $end
$var wire 1 ' qi $end
$var wire 1 " qn $end
$var wire 1 ( qni $end
$var reg 1 ) nclk $end
$scope module inst1 $end
$var wire 1 * clk $end
$var wire 1 & d $end
$var wire 1 ' q $end
$var wire 1 ( qn $end
$var reg 1 + r $end
$var reg 1 , s $end
$scope module RSlinstDl $end
$var wire 1 - r $end
$var wire 1 . s $end
$var reg 1 / q $end
$var reg 1 0 qn $end
$upscope $end
$upscope $end
$scope module inst2 $end
$var wire 1 % clk $end
$var wire 1 ' d $end
$var wire 1 ! q $end
$var wire 1 " qn $end
$var reg 1 1 r $end
$var reg 1 2 s $end
$scope module RSlinstDl $end
$var wire 1 3 r $end
$var wire 1 4 s $end
$var reg 1 5 q $end
$var reg 1 6 qn $end
$upscope $end
$upscope $end
$upscope $end
$upscope $end
$enddefinitions $end
#0
$dumpvars
x6
x5
04
03
02
01
10
0/
0.
1-
0,
1+
1*
1)
1(
0'
0&
0%
0$
0#
x"
x!
$end
#50
16
1"
05
0!
0+
0-
11
13
0)
0*
1#
1%
#60
1$
1&
#100
1/
1'
00
0(
1,
1.
01
03
1)
1*
0#
0%
#120
10
1(
0/
0'
0,
0.
1+
1-
0$
0&
#150
0+
0-
11
13
0)
0*
1#
1%
#200
1+
1-
01
03
1)
1*
0#
0%
#240
1/
1'
00
0(
1,
1.
0+
0-
1$
1&
#250
15
1!
06
0"
0,
0.
12
14
0)
0*
1#
1%
#300
1,
1.
02
04
1)
1*
0#
0%
#350
0,
0.
12
14
0)
0*
1#
1%
#360
0$
0&
#400
10
1(
0/
0'
1+
1-
02
04
1)
1*
0#
0%
#450
16
1"
05
0!
0+
0-
11
13
0)
0*
1#
1%
#480
1$
1&
#500
1/
1'
00
0(
1,
1.
01
03
1)
1*
0#
0%
#540
10
1(
0/
0'
0,
0.
1+
1-
0$
0&
#550
0+
0-
11
13
0)
0*
1#
1%
#600
1+
1-
01
03
1)
1*
0#
0%
#650
0+
0-
11
13
0)
0*
1#
1%
#700
1+
1-
01
03
1)
1*
0#
0%
#720
1/
1'
00
0(
1,
1.
0+
0-
1$
1&
#750
15
1!
06
0"
0,
0.
12
14
0)
0*
1#
1%
#780
0$
0&
#800
10
1(
0/
0'
1+
1-
02
04
1)
1*
0#
0%
#850
16
1"
05
0!
0+
0-
11
13
0)
0*
1#
1%
#900
1/
1'
00
0(
1,
1.
01
03
1)
1*
0#
0%
1$
1&
#950
15
1!
06
0"
0,
0.
12
14
0)
0*
1#
1%
#1000
1,
1.
02
04
1)
1*
0#
0%
#1050
0,
0.
12
14
0)
0*
1#
1%
#1080
0$
0&
#1100
10
1(
0/
0'
1+
1-
02
04
1)
1*
0#
0%
#1140
1/
1'
00
0(
1,
1.
0+
0-
1$
1&
#1150
0,
0.
12
14
0)
0*
1#
1%
#1200
10
1(
0/
0'
1+
1-
02
04
1)
1*
0#
0%
0$
0&
#1250
16
1"
05
0!
0+
0-
11
13
0)
0*
1#
1%
#1300
1+
1-
01
03
1)
1*
0#
0%
#1320
1/
1'
00
0(
1,
1.
0+
0-
1$
1&
#1350
15
1!
06
0"
0,
0.
12
14
0)
0*
1#
1%
#1380
0$
0&
#1400
10
1(
0/
0'
1+
1-
02
04
1)
1*
0#
0%
#1440
1/
1'
00
0(
1,
1.
0+
0-
1$
1&
#1450
0,
0.
12
14
0)
0*
1#
1%
#1500
1,
1.
02
04
1)
1*
0#
0%
#1620
10
1(
0/
0'
0,
0.
1+
1-
0$
0&
